[
    {
        "name": "子路",
        "contents": [
            {
                "dialog": "子路曰：“为孔丘。”",
                "translation": "子路说：“是孔丘。”",
                "theme": "微子篇"
            },
            {
                "dialog": "子路曰：“为仲由。”",
                "translation": "子路说：“是仲由。”",
                "theme": "微子篇"
            },
            {
                "dialog": "子路问曰：“子见夫子乎？”",
                "translation": "子路问：“您见过夫子吗？”",
                "theme": "微子篇"
            },
            {
                "dialog": "子路曰：“不仕无义。长幼之节不可废也，君臣之义如之何其废之？欲洁其身而乱大伦。君子之仕也，行其义也，道之不行已知之矣。”",
                "translation": "子路说：“不做官是不义的。长幼的节序不可废弃，君臣的义理如何能够废弃？希望洁身自好却扰乱了社会秩序。君子的做官是为了行义，知道道理不行已经很清楚了。”",
                "theme": "微子篇"
            }
        ]
    },
    {
        "name": "子贡",
        "contents": [
            {
                "dialog": "子贡曰：“君子亦有恶乎？”",
                "translation": "子贡问：“君子也有恶吗？”",
                "theme": "微子篇"
            },
            {
                "dialog": "子贡曰：“恶徼以为知者，恶不孙以为勇者，恶讦以为直者。”",
                "translation": "子贡说：“恶劣的是那些依靠投机取巧来被认为聪明的人，恶劣的是那些以不恭敬为勇敢的人，恶劣的是那些以尖刻直言为正直的人。”",
                "theme": "微子篇"
            }
        ]
    }
]
